capsule/__init__.py
capsule/app.py
capsule/decorator.py
capsule/host_api.py
capsule/http.py
capsule/py.typed
capsule_run-0.4.2.data/scripts/capsule
capsule_run-0.4.2.dist-info/METADATA
capsule_run-0.4.2.dist-info/WHEEL
capsule_run-0.4.2.dist-info/RECORD
