Metadata-Version: 2.4
Name: capsule-run
Version: 0.4.2
Classifier: Development Status :: 3 - Alpha
Classifier: Environment :: Console
Classifier: Intended Audience :: Developers
Classifier: License :: OSI Approved :: Apache Software License
Classifier: Operating System :: OS Independent
Classifier: Programming Language :: Python :: 3
Classifier: Programming Language :: Python :: 3.8
Classifier: Programming Language :: Python :: 3.9
Classifier: Programming Language :: Python :: 3.10
Classifier: Programming Language :: Python :: 3.11
Classifier: Programming Language :: Python :: 3.12
Classifier: Programming Language :: Rust
Classifier: Topic :: Security
Classifier: Topic :: Scientific/Engineering :: Artificial Intelligence
Classifier: Topic :: Software Development :: Interpreters
Requires-Dist: componentize-py>=0.19.3
Summary: Secure WASM runtime to isolate and manage AI agent tasks
Keywords: webassembly,sandbox,agents,isolation,llm,ai
Author: Capsule Contributors
License: Apache-2.0
Requires-Python: >=3.8
Project-URL: Homepage, https://github.com/mavdol/capsule
Project-URL: Repository, https://github.com/mavdol/capsule
